llmutil/__init__.py
llmutil/a.py
bfg_llmutil-0.5.5.dist-info/METADATA
bfg_llmutil-0.5.5.dist-info/WHEEL
bfg_llmutil-0.5.5.dist-info/licenses/LICENSE
bfg_llmutil-0.5.5.dist-info/RECORD
