Metadata-Version: 2.4
Name: bfg-llmutil
Version: 0.5.5
Summary: A set of utility functions to handle LLM structural output
Author-email: leizha <8961794+leizha@users.noreply.github.com>
License-File: LICENSE
Requires-Python: >=3.10
Requires-Dist: bfg-schemautil
Requires-Dist: openai
